CHANGES.md
LICENSE.md
README.md
pyproject.toml
setup.cfg
src/logoizer/__init__.py
src/logoizer/_version.py
src/logoizer/api.py
src/logoizer/cli.py
src/logoizer.egg-info/PKG-INFO
src/logoizer.egg-info/SOURCES.txt
src/logoizer.egg-info/dependency_links.txt
src/logoizer.egg-info/entry_points.txt
src/logoizer.egg-info/requires.txt
src/logoizer.egg-info/top_level.txt
src/logoizer/fonts/Quicksand/Quicksand-VariableFont_wght.ttf
src/logoizer/fonts/Quicksand/static/Quicksand-Bold.ttf
src/logoizer/fonts/Quicksand/static/Quicksand-Light.ttf
src/logoizer/fonts/Quicksand/static/Quicksand-Medium.ttf
src/logoizer/fonts/Quicksand/static/Quicksand-Regular.ttf
src/logoizer/fonts/Quicksand/static/Quicksand-SemiBold.ttf