Metadata-Version: 2.1
Name: logoizer
Version: 0.2.0.post1
Summary: Make CSDMS text logos
Author: Eric Hutton
Author-email: mcflugen@gmail.com
Maintainer: Eric Hutton
Maintainer-email: mcflugen@gmail.com
License: MIT
Project-URL: repository, https://github.com/mcflugen/logoize
Project-URL: documentation, https://github.com/mcflugen/logoizer/blob/main/README.md
Project-URL: changelog, https://github.com/mcflugen/logoizer/blob/main/CHANGES.md
Keywords: csdms,logo
Classifier: Development Status :: 2 - Pre-Alpha
Classifier: License :: OSI Approved :: MIT License
Classifier: Operating System :: OS Independent
Classifier: Programming Language :: Python :: 3.11
Classifier: Programming Language :: Python :: 3.12
Classifier: Programming Language :: Python :: 3.13
Requires-Python: >=3.11
License-File: LICENSE.md
Requires-Dist: matplotlib>=3.2
Provides-Extra: dev
Requires-Dist: black; extra == "dev"
Requires-Dist: coverage; extra == "dev"
Requires-Dist: flake8; extra == "dev"
Requires-Dist: isort; extra == "dev"
Requires-Dist: nox; extra == "dev"
Requires-Dist: pre-commit; extra == "dev"
Requires-Dist: pytest; extra == "dev"
Requires-Dist: pytest-cov; extra == "dev"
Requires-Dist: pytest-datadir; extra == "dev"
Requires-Dist: pytest-runner; extra == "dev"
Requires-Dist: towncrier; extra == "dev"
Requires-Dist: zestreleaser.towncrier; extra == "dev"
Provides-Extra: doc
Requires-Dist: sphinx; extra == "doc"
Requires-Dist: pygments>=2.4; extra == "doc"
Requires-Dist: sphinx-inline-tabs; extra == "doc"
Requires-Dist: furo; extra == "doc"
